[null,{"id":1,"atypeId":3,"description":"常见的锅盖\n它很轻，有一个手柄，所以它很容易使用","etypeId":2,"traits":[{"code":22,"dataId":1,"value":0.05}],"iconIndex":128,"name":"鍋の蓋","note":"","params":[0,0,0,4,0,2,0,0],"price":50},{"id":2,"atypeId":3,"description":"给洋娃娃戴的头盔\n虽然没有实用性，但总比什么都没有好一些","etypeId":3,"traits":[{"code":22,"dataId":1,"value":0}],"iconIndex":130,"name":"おもちゃのかぶと","note":"","params":[0,0,0,6,0,0,0,0],"price":0},{"id":3,"atypeId":1,"description":"杰斯学园的制服\n移动方便，设计也获得高度评价","etypeId":4,"traits":[{"code":22,"dataId":1,"value":0.01}],"iconIndex":135,"name":"学生服","note":"","params":[0,0,0,2,0,0,0,0],"price":100},{"id":4,"atypeId":3,"description":"容器の蓋\n戴上它可以保护头部","etypeId":3,"traits":[{"code":22,"dataId":1,"value":0}],"iconIndex":130,"name":"ドリンクの蓋","note":"","params":[0,0,0,3,0,0,0,0],"price":0},{"id":5,"atypeId":3,"description":"由粘液制成的吊坠\n滑溜溜的，一部分粉丝的评价很高","etypeId":5,"traits":[{"code":22,"dataId":1,"value":0.03}],"iconIndex":146,"name":"スライム・ペンダント","note":"","params":[0,0,0,2,0,2,0,0],"price":100},{"id":6,"atypeId":3,"description":"用年轻精灵的头发制作的护身符会保护佩戴者\n说给予。只是因为这个经常发生悲伤的事件。","etypeId":5,"traits":[{"code":22,"dataId":1,"value":0.03}],"iconIndex":149,"name":"エルフの髪のお守り","note":"","params":[10,0,1,4,1,15,0,1],"price":0},{"id":7,"atypeId":3,"description":"给娃娃穿的玩具盔甲\n虽然不实用，但比普通衣服要好一些","etypeId":4,"traits":[{"code":22,"dataId":1,"value":0}],"iconIndex":136,"name":"おもちゃのよろい","note":"","params":[0,0,0,6,0,0,0,0],"price":0},{"id":8,"atypeId":4,"description":"饰有学园学生栽培的花朵的学园限定别针\n虽然不华丽，但是朴素可爱，广受好评","etypeId":3,"traits":[{"code":22,"dataId":1,"value":0}],"iconIndex":148,"name":"花ピン","note":"","params":[0,0,0,10,0,10,0,0],"price":50},{"id":9,"atypeId":3,"description":"以魔法蘑菇的伞部作为盾牌的防具\n对魔法有耐性","etypeId":2,"traits":[{"code":22,"dataId":1,"value":0}],"iconIndex":129,"name":"マジックキノコの傘","note":"","params":[0,0,0,1,0,7,0,0],"price":10},{"id":10,"atypeId":3,"description":"由冰精灵制成的冰制成的盾牌\n对冰和风有抵抗力","etypeId":2,"traits":[{"code":22,"dataId":1,"value":0},{"code":11,"dataId":3,"value":0.85},{"code":11,"dataId":7,"value":0.85}],"iconIndex":129,"name":"魔精の盾","note":"氷　85％\n風　85％","params":[0,0,0,5,0,0,0,0],"price":0},{"id":11,"atypeId":3,"description":"用手指植物的叶子制成的日本短外套\n变得耐水和耐土壤","etypeId":4,"traits":[{"code":11,"dataId":7,"value":0.85},{"code":11,"dataId":6,"value":0.85}],"iconIndex":139,"name":"指取かっぱ","note":"風　85％\n土　85％","params":[0,0,0,8,0,2,0,0],"price":150},{"id":12,"atypeId":3,"description":"小妖精自制的头巾\n虽然设计粗糙，但能很好地保护头部","etypeId":3,"traits":[{"code":22,"dataId":1,"value":0},{"code":11,"dataId":4,"value":0.9},{"code":11,"dataId":7,"value":0.9},{"code":11,"dataId":6,"value":0.9}],"iconIndex":131,"name":"ゴブリンちゃん手製頭巾","note":"雷　90％\n風　90％\n土　90％","params":[0,0,0,11,0,0,0,0],"price":0},{"id":13,"atypeId":3,"description":"「守护国家与王国民」的王国骑士团护身符复制品\n我觉得穿在身上就会很结实","etypeId":5,"traits":[{"code":22,"dataId":1,"value":-0.02}],"iconIndex":147,"name":"騎士団のお守り","note":"","params":[0,0,0,10,0,0,0,0],"price":0},{"id":14,"atypeId":3,"description":"由哈图森林的树木制成的头盔形状的钥匙圈\n坚硬，结实，但速度稍慢","etypeId":3,"traits":[{"code":22,"dataId":1,"value":0}],"iconIndex":131,"name":"木の被り物","note":"","params":[0,0,0,9,0,2,-2,0],"price":100},{"id":15,"atypeId":3,"description":"「勇者人形系列」中黑暗剑士拉威尔所持的盾\n虽然是玩具，但还算结实","etypeId":2,"traits":[{"code":22,"dataId":1,"value":0},{"code":11,"dataId":9,"value":0.5}],"iconIndex":128,"name":"漆黒の盾","note":"闇　50％\n","params":[0,0,0,10,0,0,0,0],"price":550},{"id":16,"atypeId":3,"description":"希拉里很少脱下的长袍\n像希拉里一样躲避敌人的攻击","etypeId":4,"traits":[{"code":22,"dataId":1,"value":0.15}],"iconIndex":139,"name":"ヒラリローブ","note":"","params":[0,0,0,3,0,1,0,0],"price":0},{"id":17,"atypeId":3,"description":"魔法生物（失敗作）の一部\n只要穿上就能稍微提升咒语的威力","etypeId":5,"traits":[{"code":22,"dataId":1,"value":0}],"iconIndex":149,"name":"魔力の塊","note":"","params":[0,0,0,0,10,0,0,0],"price":0},{"id":18,"atypeId":3,"description":"出自《勇者人形系列》的暗剑士拉威尔的头盔\n虽然是玩具，但还算结实","etypeId":3,"traits":[{"code":22,"dataId":1,"value":0},{"code":11,"dataId":9,"value":0.5}],"iconIndex":132,"name":"漆黒の兜","note":"闇　50％","params":[0,0,0,10,0,0,0,0],"price":550},{"id":19,"atypeId":3,"description":"将彷徨的史莱姆直接披上的原始铠甲\n对打击和雷电较强，但对火焰、风和土壤较弱","etypeId":4,"traits":[{"code":22,"dataId":1,"value":0},{"code":11,"dataId":4,"value":0.5},{"code":11,"dataId":1,"value":0.85},{"code":11,"dataId":2,"value":1.3},{"code":11,"dataId":7,"value":1.3},{"code":11,"dataId":6,"value":1.3}],"iconIndex":136,"name":"スライムアーマー","note":"雷　50％\n物理　85％\n炎　130％\n風　130％\n土　130％","params":[0,0,0,13,0,0,0,0],"price":300},{"id":20,"atypeId":3,"description":"发给王国骑士团成员的头盔\n虽然轻便坚固，但在设计方面需要改良","etypeId":3,"traits":[{"code":22,"dataId":1,"value":0},{"code":53,"dataId":3,"value":1}],"iconIndex":132,"name":"王国騎士団の兜","note":"","params":[0,0,0,25,0,0,0,0],"price":0},{"id":21,"atypeId":3,"description":"支付给王国骑士团成员的铠甲\n它看起来像裙子，但它比商业上的盔甲更好","etypeId":4,"traits":[{"code":22,"dataId":1,"value":0},{"code":53,"dataId":4,"value":1}],"iconIndex":132,"name":"王国騎士団のドレス鎧","note":"","params":[0,0,0,25,0,0,0,0],"price":0},{"id":22,"atypeId":3,"description":"支付给王国骑士团团员的盾\n小而结实，不妨碍剑","etypeId":2,"traits":[{"code":22,"dataId":1,"value":0},{"code":53,"dataId":3,"value":1},{"code":53,"dataId":2,"value":1}],"iconIndex":132,"name":"王国騎士団の盾","note":"","params":[0,0,0,20,0,0,0,0],"price":0},{"id":23,"atypeId":3,"description":"一枚银戒指，上面刻有 jaak 教团的纹样\n犹豫要不要加上什么邪恶的东西","etypeId":5,"traits":[{"code":22,"dataId":1,"value":-0.02}],"iconIndex":144,"name":"ジャアクのシルバーリング","note":"","params":[0,0,3,5,3,5,-2,-3],"price":0},{"id":24,"atypeId":7,"description":"幽灵君身上的斗篷\n","etypeId":4,"traits":[{"code":22,"dataId":1,"value":0},{"code":53,"dataId":4,"value":1}],"iconIndex":139,"name":"ゴースト・マント","note":"","params":[0,0,0,0,0,0,0,0],"price":0},{"id":25,"atypeId":7,"description":"白灵戴的黑色戒指","etypeId":5,"traits":[{"code":22,"dataId":1,"value":0},{"code":53,"dataId":5,"value":1}],"iconIndex":145,"name":"ゴーストリング","note":"","params":[0,0,0,0,5,5,5,0],"price":0},{"id":26,"atypeId":3,"description":"一件巨大的白色防护服\n有一种神秘的技术可以消除身体的麻痹感","etypeId":4,"traits":[{"code":22,"dataId":1,"value":0},{"code":14,"dataId":13,"value":1}],"iconIndex":137,"name":"探査用防護服","note":"麻痺　無効","params":[0,0,0,15,0,0,0,0],"price":0},{"id":27,"atypeId":3,"description":"一个巨大的白色头盔\n有一种神秘的技术可以清除空气中的毒素","etypeId":3,"traits":[{"code":22,"dataId":1,"value":0},{"code":14,"dataId":4,"value":1}],"iconIndex":137,"name":"探査用防護ヘルメット","note":"毒　無効","params":[0,0,0,15,0,0,0,0],"price":0},{"id":28,"atypeId":3,"description":"用甲壳虫作为盾牌的东西\n每次我移动它，它就会叮当作响","etypeId":2,"traits":[{"code":22,"dataId":1,"value":0},{"code":11,"dataId":2,"value":1.2},{"code":11,"dataId":6,"value":0.5},{"code":11,"dataId":7,"value":0.7}],"iconIndex":128,"name":"ガジャガジャ・シールド","note":"炎　120％\n土　50％\n風　70％","params":[0,0,0,14,0,0,0,0],"price":0},{"id":29,"atypeId":4,"description":"褶边长袜\n可以使用「女仆的打扫时间」","etypeId":4,"traits":[{"code":22,"dataId":1,"value":0},{"code":43,"dataId":101,"value":1}],"iconIndex":141,"name":"メイド・ストッキング","note":"","params":[0,0,10,10,0,0,1,0],"price":0},{"id":30,"atypeId":3,"description":"最強！","etypeId":4,"traits":[{"code":22,"dataId":1,"value":0}],"iconIndex":137,"name":"デバック鎧","note":"","params":[0,0,500,500,0,500,500,0],"price":0},{"id":31,"atypeId":0,"description":"","etypeId":2,"traits":[{"code":22,"dataId":1,"value":0}],"iconIndex":0,"name":"","note":"","params":[0,0,0,0,0,0,0,0],"price":0},{"id":32,"atypeId":0,"description":"","etypeId":2,"traits":[{"code":22,"dataId":1,"value":0}],"iconIndex":0,"name":"","note":"","params":[0,0,0,0,0,0,0,0],"price":0},{"id":33,"atypeId":0,"description":"","etypeId":2,"traits":[{"code":22,"dataId":1,"value":0}],"iconIndex":0,"name":"","note":"","params":[0,0,0,0,0,0,0,0],"price":0},{"id":34,"atypeId":0,"description":"","etypeId":2,"traits":[{"code":22,"dataId":1,"value":0}],"iconIndex":0,"name":"","note":"","params":[0,0,0,0,0,0,0,0],"price":0},{"id":35,"atypeId":0,"description":"","etypeId":2,"traits":[{"code":22,"dataId":1,"value":0}],"iconIndex":0,"name":"","note":"","params":[0,0,0,0,0,0,0,0],"price":0},{"id":36,"atypeId":0,"description":"","etypeId":2,"traits":[{"code":22,"dataId":1,"value":0}],"iconIndex":0,"name":"","note":"","params":[0,0,0,0,0,0,0,0],"price":0},{"id":37,"atypeId":0,"description":"","etypeId":2,"traits":[{"code":22,"dataId":1,"value":0}],"iconIndex":0,"name":"","note":"","params":[0,0,0,0,0,0,0,0],"price":0},{"id":38,"atypeId":0,"description":"","etypeId":2,"traits":[{"code":22,"dataId":1,"value":0}],"iconIndex":0,"name":"","note":"","params":[0,0,0,0,0,0,0,0],"price":0},{"id":39,"atypeId":0,"description":"","etypeId":2,"traits":[{"code":22,"dataId":1,"value":0}],"iconIndex":0,"name":"","note":"","params":[0,0,0,0,0,0,0,0],"price":0},{"id":40,"atypeId":0,"description":"","etypeId":2,"traits":[{"code":22,"dataId":1,"value":0}],"iconIndex":0,"name":"","note":"","params":[0,0,0,0,0,0,0,0],"price":0},{"id":41,"atypeId":0,"description":"","etypeId":2,"traits":[{"code":22,"dataId":1,"value":0}],"iconIndex":0,"name":"","note":"","params":[0,0,0,0,0,0,0,0],"price":0},{"id":42,"atypeId":0,"description":"","etypeId":2,"traits":[{"code":22,"dataId":1,"value":0}],"iconIndex":0,"name":"","note":"","params":[0,0,0,0,0,0,0,0],"price":0},{"id":43,"atypeId":0,"description":"","etypeId":2,"traits":[{"code":22,"dataId":1,"value":0}],"iconIndex":0,"name":"","note":"","params":[0,0,0,0,0,0,0,0],"price":0},{"id":44,"atypeId":0,"description":"","etypeId":2,"traits":[{"code":22,"dataId":1,"value":0}],"iconIndex":0,"name":"","note":"","params":[0,0,0,0,0,0,0,0],"price":0},{"id":45,"atypeId":0,"description":"","etypeId":2,"traits":[{"code":22,"dataId":1,"value":0}],"iconIndex":0,"name":"","note":"","params":[0,0,0,0,0,0,0,0],"price":0},{"id":46,"atypeId":0,"description":"","etypeId":2,"traits":[{"code":22,"dataId":1,"value":0}],"iconIndex":0,"name":"","note":"","params":[0,0,0,0,0,0,0,0],"price":0},{"id":47,"atypeId":0,"description":"","etypeId":2,"traits":[{"code":22,"dataId":1,"value":0}],"iconIndex":0,"name":"","note":"","params":[0,0,0,0,0,0,0,0],"price":0},{"id":48,"atypeId":0,"description":"","etypeId":2,"traits":[{"code":22,"dataId":1,"value":0}],"iconIndex":0,"name":"","note":"","params":[0,0,0,0,0,0,0,0],"price":0},{"id":49,"atypeId":0,"description":"","etypeId":2,"traits":[{"code":22,"dataId":1,"value":0}],"iconIndex":0,"name":"","note":"","params":[0,0,0,0,0,0,0,0],"price":0},{"id":50,"atypeId":0,"description":"","etypeId":2,"traits":[{"code":22,"dataId":1,"value":0}],"iconIndex":0,"name":"","note":"","params":[0,0,0,0,0,0,0,0],"price":0}]